{"cameraMode":{"drawMode":0,"name":"Shaded","section":"Shading Mode"},"sceneLighting":true,"audioPlay":false,"sceneViewState":{"showFog":true,"showMaterialUpdate":false,"showSkybox":true,"showFlares":true,"showImageEffects":true,"showParticleSystems":true},"in2DMode":false,"pivot":{"x":26.360002517700197,"y":15.450002670288086,"z":73.33000183105469},"rotation":{"x":0.17451797425746919,"y":0.7548913955688477,"z":-0.2226489633321762,"w":0.5917044878005981},"size":15.485882759094239,"orthographic":false}